GNBdistributions/Binomialdistribution.py
GNBdistributions/Gaussiandistribution.py
GNBdistributions/Generaldistribution.py
GNBdistributions/__init__.py
GNBdistributions-0.2.dist-info/DESCRIPTION.rst
GNBdistributions-0.2.dist-info/METADATA
GNBdistributions-0.2.dist-info/RECORD
GNBdistributions-0.2.dist-info/WHEEL
GNBdistributions-0.2.dist-info/metadata.json
GNBdistributions-0.2.dist-info/top_level.txt
