Metadata-Version: 2.0
Name: GNBdistributions
Version: 0.2
Summary: Gaussian distributions
Home-page: UNKNOWN
Author: UNKNOWN
Author-email: UNKNOWN
License: UNKNOWN
Platform: UNKNOWN
